CHANGELOG.rst
LICENSE.txt
MANIFEST.in
README.rst
setup.cfg
setup.py
doc/Makefile
doc/conf.py
doc/index.rst
fzm_python_migrations.egg-info/PKG-INFO
fzm_python_migrations.egg-info/SOURCES.txt
fzm_python_migrations.egg-info/dependency_links.txt
fzm_python_migrations.egg-info/entry_points.txt
fzm_python_migrations.egg-info/requires.txt
fzm_python_migrations.egg-info/top_level.txt
yoyo/__init__.py
yoyo/__main__.py
yoyo/backends.py
yoyo/config.py
yoyo/connections.py
yoyo/exceptions.py
yoyo/migrations.py
yoyo/utils.py
yoyo/internalmigrations/__init__.py
yoyo/internalmigrations/v1.py
yoyo/internalmigrations/v2.py
yoyo/scripts/__init__.py
yoyo/scripts/main.py
yoyo/scripts/migrate.py
yoyo/scripts/newmigration.py
yoyo/tests/migrations/test-pkg-migration.py