Metadata-Version: 2.1
Name: fzm-python-migrations
Version: 0.1.3
Summary: Database migrations with SQL
Home-page: https://ollycope.com/software/yoyo/latest/
Author: Oliver Cope
Author-email: firstw927@gmail.com
License: Apache
Keywords: migrations migrate database alembic south
Platform: UNKNOWN
Classifier: Development Status :: 5 - Production/Stable
Classifier: Environment :: Console
Classifier: Intended Audience :: Developers
Classifier: License :: OSI Approved :: Apache Software License
Classifier: Operating System :: OS Independent
Classifier: Topic :: Database
Classifier: Topic :: Database :: Front-Ends
Classifier: Topic :: Software Development
Classifier: Topic :: Software Development :: Version Control
Classifier: Programming Language :: Python :: 3
Provides-Extra: mysql
Provides-Extra: postgres
Provides-Extra: pyodbc
License-File: LICENSE.txt
